midea_inventor_lib/__init__.py
midea_inventor_lib/midea_client.py
midea_inventor_lib/midea_databody_dehumi_query.py
midea_inventor_lib/midea_databody_dehumi_request.py
midea_inventor_lib/midea_databody_dehumi_response.py
midea_inventor_lib/midea_dehumidification_device.py
midea_inventor_lib/midea_fcCon.py
midea_inventor_lib/midea_security.py
midea_inventor_dehumidifier-1.0.0.dist-info/AUTHORS
midea_inventor_dehumidifier-1.0.0.dist-info/LICENSE
midea_inventor_dehumidifier-1.0.0.dist-info/METADATA
midea_inventor_dehumidifier-1.0.0.dist-info/WHEEL
midea_inventor_dehumidifier-1.0.0.dist-info/top_level.txt
midea_inventor_dehumidifier-1.0.0.dist-info/RECORD
